[
  {
    "id": "id-1760431919457ce7e1c6b8f0ce8",
    "content": "上周四数学两道大题，没算出来的同学再自己算一遍，其他就自己整理错题吧",
    "publisher": "文瑞雪",
    "created": 1760431919,
    "updated": null
  },
  {
    "id": "id-1760430511244645293e6c1bcf8",
    "content": "本周四10:20-12:00体测",
    "publisher": "文瑞雪",
    "created": 1760430511,
    "updated": null
  },
  {
    "id": "id-17604223351722f70ee2d3f507",
    "content": "请参加开幕式的所有同学于周三中午12:20到圆厅排练。\n学号：2 3 5 6 8 11 12 13 14 17 18 19 22 23 25 27 29 30 32 33 35 37 38 39 40 41",
    "publisher": "匿名",
    "created": 1760422335,
    "updated": null
  },
  {
    "id": "id-176034339208972ad9cd4c1586",
    "content": "孙运龙来抱练习册，今天作业写作业1.3",
    "publisher": "文瑞雪",
    "created": 1760343392,
    "updated": null
  }
]