[
  {
    "id": "id-176008288528952dacea675995",
    "content": "周六语文和数学对调",
    "publisher": "文瑞雪",
    "created": 1760082885,
    "updated": null
  },
  {
    "id": "id-1760065693965cd16e524aae8c8",
    "content": "今天下午大扫除，中午不用值日，全员起椅子",
    "publisher": "文瑞雪",
    "created": 1760065693,
    "updated": 1760082858
  },
  {
    "id": "id-1759981323187a954f28fdd0008",
    "content": "我在桌上贴了两张随意贴，用于预约评卷时间，想要评卷的同学可以来自行填写，按时间来",
    "publisher": "文瑞雪",
    "created": 1759981323,
    "updated": null
  }
]