{
    "code": 200,
    "msg": "数据请求成功",
    "data": [
        {
            "hot": "107万",
            "index": 1,
            "title": "央视秋晚汶川3分钟太催泪",
            "url": "https://s.weibo.com/weibo?q=央视秋晚汶川3分钟太催泪"
        },
        {
            "hot": "45万",
            "index": 2,
            "title": "月亮",
            "url": "https://s.weibo.com/weibo?q=月亮"
        },
        {
            "hot": "42万",
            "index": 3,
            "title": "圆圆圆圆中秋圆圆圆圆",
            "url": "https://s.weibo.com/weibo?q=圆圆圆圆中秋圆圆圆圆"
        },
        {
            "hot": "41万",
            "index": 4,
            "title": "挪威2万人口小岛因中国游客堵车",
            "url": "https://s.weibo.com/weibo?q=挪威2万人口小岛因中国游客堵车"
        },
        {
            "hot": "23万",
            "index": 5,
            "title": "诺贝尔奖奖金124年没花完",
            "url": "https://s.weibo.com/weibo?q=诺贝尔奖奖金124年没花完"
        },
        {
            "hot": "22万",
            "index": 6,
            "title": "最好的睡姿vs最差的睡姿",
            "url": "https://s.weibo.com/weibo?q=最好的睡姿vs最差的睡姿"
        },
        {
            "hot": "22万",
            "index": 7,
            "title": "避雷这10个养生误区",
            "url": "https://s.weibo.com/weibo?q=避雷这10个养生误区"
        },
        {
            "hot": "22万",
            "index": 8,
            "title": "超级月亮",
            "url": "https://s.weibo.com/weibo?q=超级月亮"
        },
        {
            "hot": "22万",
            "index": 9,
            "title": "王楚钦中国大满贯后发文",
            "url": "https://s.weibo.com/weibo?q=王楚钦中国大满贯后发文"
        },
        {
            "hot": "21万",
            "index": 10,
            "title": "央视中秋晚会",
            "url": "https://s.weibo.com/weibo?q=央视中秋晚会"
        },
        {
            "hot": "21万",
            "index": 11,
            "title": "央视中秋晚会节目单",
            "url": "https://s.weibo.com/weibo?q=央视中秋晚会节目单"
        },
        {
            "hot": "21万",
            "index": 12,
            "title": "谢娜 央视主持",
            "url": "https://s.weibo.com/weibo?q=谢娜 央视主持"
        },
        {
            "hot": "21万",
            "index": 13,
            "title": "赵今麦在国外美成啥了",
            "url": "https://s.weibo.com/weibo?q=赵今麦在国外美成啥了"
        },
        {
            "hot": "21万",
            "index": 14,
            "title": "王源 马尔代夫",
            "url": "https://s.weibo.com/weibo?q=王源 马尔代夫"
        },
        {
            "hot": "21万",
            "index": 15,
            "title": "鹿晗方将承担机票和酒店产生的损失",
            "url": "https://s.weibo.com/weibo?q=鹿晗方将承担机票和酒店产生的损失"
        },
        {
            "hot": "21万",
            "index": 16,
            "title": "周深中俄双语致敬英烈",
            "url": "https://s.weibo.com/weibo?q=周深中俄双语致敬英烈"
        },
        {
            "hot": "21万",
            "index": 17,
            "title": "唐嫣美成啥了 欧豪也是个神",
            "url": "https://s.weibo.com/weibo?q=唐嫣美成啥了 欧豪也是个神"
        },
        {
            "hot": "21万",
            "index": 18,
            "title": "张艺兴演唱会",
            "url": "https://s.weibo.com/weibo?q=张艺兴演唱会"
        },
        {
            "hot": "21万",
            "index": 19,
            "title": "石凯回复",
            "url": "https://s.weibo.com/weibo?q=石凯回复"
        },
        {
            "hot": "21万",
            "index": 20,
            "title": "多名中国公民在澳徒步登山身亡",
            "url": "https://s.weibo.com/weibo?q=多名中国公民在澳徒步登山身亡"
        },
        {
            "hot": "21万",
            "index": 21,
            "title": "周深 三十岁了已经不可爱了",
            "url": "https://s.weibo.com/weibo?q=周深 三十岁了已经不可爱了"
        },
        {
            "hot": "21万",
            "index": 22,
            "title": "素颜的刘浩存赵今麦李庚希",
            "url": "https://s.weibo.com/weibo?q=素颜的刘浩存赵今麦李庚希"
        },
        {
            "hot": "21万",
            "index": 23,
            "title": "张艺兴演唱会唱了十二月的奇迹",
            "url": "https://s.weibo.com/weibo?q=张艺兴演唱会唱了十二月的奇迹"
        },
        {
            "hot": "21万",
            "index": 24,
            "title": "李沁 英气",
            "url": "https://s.weibo.com/weibo?q=李沁 英气"
        },
        {
            "hot": "21万",
            "index": 25,
            "title": "侯佩岑主持央视秋晚",
            "url": "https://s.weibo.com/weibo?q=侯佩岑主持央视秋晚"
        },
        {
            "hot": "20万",
            "index": 26,
            "title": "月入3万存2万五的真实生活",
            "url": "https://s.weibo.com/weibo?q=月入3万存2万五的真实生活"
        },
        {
            "hot": "19万",
            "index": 27,
            "title": "十个勤天每一句都唱到心上了",
            "url": "https://s.weibo.com/weibo?q=十个勤天每一句都唱到心上了"
        },
        {
            "hot": "16万",
            "index": 28,
            "title": "檀健次叶世荣动了谁的DNA",
            "url": "https://s.weibo.com/weibo?q=檀健次叶世荣动了谁的DNA"
        },
        {
            "hot": "15万",
            "index": 29,
            "title": "偷偷藏不住中秋节售后",
            "url": "https://s.weibo.com/weibo?q=偷偷藏不住中秋节售后"
        },
        {
            "hot": "15万",
            "index": 30,
            "title": "闫妮不微醺了",
            "url": "https://s.weibo.com/weibo?q=闫妮不微醺了"
        },
        {
            "hot": "15万",
            "index": 31,
            "title": "刘一菲cos灵儿",
            "url": "https://s.weibo.com/weibo?q=刘一菲cos灵儿"
        },
        {
            "hot": "14万",
            "index": 32,
            "title": "许我耀眼",
            "url": "https://s.weibo.com/weibo?q=许我耀眼"
        },
        {
            "hot": "13万",
            "index": 33,
            "title": "谢霆锋演唱会",
            "url": "https://s.weibo.com/weibo?q=谢霆锋演唱会"
        },
        {
            "hot": "13万",
            "index": 34,
            "title": "愿你心怀皓月步履不停",
            "url": "https://s.weibo.com/weibo?q=愿你心怀皓月步履不停"
        },
        {
            "hot": "13万",
            "index": 35,
            "title": "魏哲鸣沈月我的老公老婆同台了",
            "url": "https://s.weibo.com/weibo?q=魏哲鸣沈月我的老公老婆同台了"
        },
        {
            "hot": "12万",
            "index": 36,
            "title": "王橹杰中秋祝福",
            "url": "https://s.weibo.com/weibo?q=王橹杰中秋祝福"
        },
        {
            "hot": "12万",
            "index": 37,
            "title": "陈奕恒高会",
            "url": "https://s.weibo.com/weibo?q=陈奕恒高会"
        },
        {
            "hot": "12万",
            "index": 38,
            "title": "韩国疗养院给老人服用大量安眠药",
            "url": "https://s.weibo.com/weibo?q=韩国疗养院给老人服用大量安眠药"
        },
        {
            "hot": "12万",
            "index": 39,
            "title": "央视审美 国泰民安",
            "url": "https://s.weibo.com/weibo?q=央视审美 国泰民安"
        },
        {
            "hot": "11万",
            "index": 40,
            "title": "王艺迪总结中国大满贯",
            "url": "https://s.weibo.com/weibo?q=王艺迪总结中国大满贯"
        },
        {
            "hot": "11万",
            "index": 41,
            "title": "中秋晚会没有何炅",
            "url": "https://s.weibo.com/weibo?q=中秋晚会没有何炅"
        },
        {
            "hot": "11万",
            "index": 42,
            "title": "10月6日再逢中秋要等到2063年",
            "url": "https://s.weibo.com/weibo?q=10月6日再逢中秋要等到2063年"
        },
        {
            "hot": "11万",
            "index": 43,
            "title": "王楚钦你扣子扣岔了",
            "url": "https://s.weibo.com/weibo?q=王楚钦你扣子扣岔了"
        },
        {
            "hot": "11万",
            "index": 44,
            "title": "于适蒋勤勤月光完整版",
            "url": "https://s.weibo.com/weibo?q=于适蒋勤勤月光完整版"
        },
        {
            "hot": "11万",
            "index": 45,
            "title": "打卡最美月亮",
            "url": "https://s.weibo.com/weibo?q=打卡最美月亮"
        },
        {
            "hot": "11万",
            "index": 46,
            "title": "陈哲远G社生图状态",
            "url": "https://s.weibo.com/weibo?q=陈哲远G社生图状态"
        },
        {
            "hot": "11万",
            "index": 47,
            "title": "烘焙店老板被新员工当成小偷",
            "url": "https://s.weibo.com/weibo?q=烘焙店老板被新员工当成小偷"
        },
        {
            "hot": "11万",
            "index": 48,
            "title": "易烊千玺 有人正在挂念你",
            "url": "https://s.weibo.com/weibo?q=易烊千玺 有人正在挂念你"
        },
        {
            "hot": "11万",
            "index": 49,
            "title": "金莎这小两口 越看越般配",
            "url": "https://s.weibo.com/weibo?q=金莎这小两口 越看越般配"
        },
        {
            "hot": "11万",
            "index": 50,
            "title": "谢娜一本正经",
            "url": "https://s.weibo.com/weibo?q=谢娜一本正经"
        },
        {
            "hot": "11万",
            "index": 51,
            "title": "时代少年团高会直播",
            "url": "https://s.weibo.com/weibo?q=时代少年团高会直播"
        }
    ],
    "request_id": "c5f4dc8822bd791ac6b61eb0"
}