{
    "code": 200,
    "msg": "数据请求成功",
    "data": [
        {
            "hot": "113万",
            "index": 1,
            "title": "一念江南",
            "url": "https://s.weibo.com/weibo?q=一念江南"
        },
        {
            "hot": "71万",
            "index": 2,
            "title": "美团将全面取消骑手超时罚款",
            "url": "https://s.weibo.com/weibo?q=美团将全面取消骑手超时罚款"
        },
        {
            "hot": "62万",
            "index": 3,
            "title": "阅兵训练场革命先辈的精神具象化了",
            "url": "https://s.weibo.com/weibo?q=阅兵训练场革命先辈的精神具象化了"
        },
        {
            "hot": "61万",
            "index": 4,
            "title": "七夕送礼上淘宝低至7.9折",
            "url": "https://s.weibo.com/weibo?q=七夕送礼上淘宝低至7.9折"
        },
        {
            "hot": "57万",
            "index": 5,
            "title": "终于有人吐槽内娱高奢花式title",
            "url": "https://s.weibo.com/weibo?q=终于有人吐槽内娱高奢花式title"
        },
        {
            "hot": "52万",
            "index": 6,
            "title": "多方回应胖东来免费筷子无标签被起诉",
            "url": "https://s.weibo.com/weibo?q=多方回应胖东来免费筷子无标签被起诉"
        },
        {
            "hot": "32万",
            "index": 7,
            "title": "什么样的泡面才是最好吃的",
            "url": "https://s.weibo.com/weibo?q=什么样的泡面才是最好吃的"
        },
        {
            "hot": "31万",
            "index": 8,
            "title": "捷途纵横G700全球盲订开启",
            "url": "https://s.weibo.com/weibo?q=捷途纵横G700全球盲订开启"
        },
        {
            "hot": "30万",
            "index": 9,
            "title": "原房主跳楼身亡房子1457000元拍出",
            "url": "https://s.weibo.com/weibo?q=原房主跳楼身亡房子1457000元拍出"
        },
        {
            "hot": "29万",
            "index": 10,
            "title": "小蝶退役",
            "url": "https://s.weibo.com/weibo?q=小蝶退役"
        },
        {
            "hot": "24万",
            "index": 11,
            "title": "40天婴儿肝硬化00后父亲割肝救女",
            "url": "https://s.weibo.com/weibo?q=40天婴儿肝硬化00后父亲割肝救女"
        },
        {
            "hot": "22万",
            "index": 12,
            "title": "苏醒回应披哥摆烂",
            "url": "https://s.weibo.com/weibo?q=苏醒回应披哥摆烂"
        },
        {
            "hot": "22万",
            "index": 13,
            "title": "刘美含 张远",
            "url": "https://s.weibo.com/weibo?q=刘美含 张远"
        },
        {
            "hot": "22万",
            "index": 14,
            "title": "老潘财商发声明",
            "url": "https://s.weibo.com/weibo?q=老潘财商发声明"
        },
        {
            "hot": "22万",
            "index": 15,
            "title": "伊利回应虞书欣代言",
            "url": "https://s.weibo.com/weibo?q=伊利回应虞书欣代言"
        },
        {
            "hot": "21万",
            "index": 16,
            "title": "宋浩然 赘婿不是人吗",
            "url": "https://s.weibo.com/weibo?q=宋浩然 赘婿不是人吗"
        },
        {
            "hot": "21万",
            "index": 17,
            "title": "宋丹丹和林永健儿子一起庆生",
            "url": "https://s.weibo.com/weibo?q=宋丹丹和林永健儿子一起庆生"
        },
        {
            "hot": "21万",
            "index": 18,
            "title": "金莎孙丞潇七夕聊天记录",
            "url": "https://s.weibo.com/weibo?q=金莎孙丞潇七夕聊天记录"
        },
        {
            "hot": "21万",
            "index": 19,
            "title": "奥迪回应字母标",
            "url": "https://s.weibo.com/weibo?q=奥迪回应字母标"
        },
        {
            "hot": "21万",
            "index": 20,
            "title": "泰国总理佩通坦遭解职",
            "url": "https://s.weibo.com/weibo?q=泰国总理佩通坦遭解职"
        },
        {
            "hot": "21万",
            "index": 21,
            "title": "刘美含 15年10个字52分钟",
            "url": "https://s.weibo.com/weibo?q=刘美含 15年10个字52分钟"
        },
        {
            "hot": "21万",
            "index": 22,
            "title": "始祖鸟4位数徒步鞋不到一周就开胶",
            "url": "https://s.weibo.com/weibo?q=始祖鸟4位数徒步鞋不到一周就开胶"
        },
        {
            "hot": "21万",
            "index": 23,
            "title": "中共中央政治局召开会议",
            "url": "https://s.weibo.com/weibo?q=中共中央政治局召开会议"
        },
        {
            "hot": "19万",
            "index": 24,
            "title": "宋轶御姐黑长直",
            "url": "https://s.weibo.com/weibo?q=宋轶御姐黑长直"
        },
        {
            "hot": "18万",
            "index": 25,
            "title": "顾客起诉胖东来免费筷子无标签",
            "url": "https://s.weibo.com/weibo?q=顾客起诉胖东来免费筷子无标签"
        },
        {
            "hot": "15万",
            "index": 26,
            "title": "万斯称若特朗普遇不测已准备好接班",
            "url": "https://s.weibo.com/weibo?q=万斯称若特朗普遇不测已准备好接班"
        },
        {
            "hot": "14万",
            "index": 27,
            "title": "田曦薇粉色玛丽猫",
            "url": "https://s.weibo.com/weibo?q=田曦薇粉色玛丽猫"
        },
        {
            "hot": "14万",
            "index": 28,
            "title": "当第一批二次元成为家长后",
            "url": "https://s.weibo.com/weibo?q=当第一批二次元成为家长后"
        },
        {
            "hot": "14万",
            "index": 29,
            "title": "宠物喂食器 泄露隐私",
            "url": "https://s.weibo.com/weibo?q=宠物喂食器 泄露隐私"
        },
        {
            "hot": "13万",
            "index": 30,
            "title": "何晟铭 再见了白月光",
            "url": "https://s.weibo.com/weibo?q=何晟铭 再见了白月光"
        },
        {
            "hot": "13万",
            "index": 31,
            "title": "辛巴宣布退网后直播连麦带货",
            "url": "https://s.weibo.com/weibo?q=辛巴宣布退网后直播连麦带货"
        },
        {
            "hot": "13万",
            "index": 32,
            "title": "落石砸车致死案一审未当庭宣判",
            "url": "https://s.weibo.com/weibo?q=落石砸车致死案一审未当庭宣判"
        },
        {
            "hot": "12万",
            "index": 33,
            "title": "法国上万未成年少女从事色情行业",
            "url": "https://s.weibo.com/weibo?q=法国上万未成年少女从事色情行业"
        },
        {
            "hot": "12万",
            "index": 34,
            "title": "七夕",
            "url": "https://s.weibo.com/weibo?q=七夕"
        },
        {
            "hot": "12万",
            "index": 35,
            "title": "张凌赫突然睡醒发七夕快乐",
            "url": "https://s.weibo.com/weibo?q=张凌赫突然睡醒发七夕快乐"
        },
        {
            "hot": "12万",
            "index": 36,
            "title": "关晓彤王牌对王牌造型",
            "url": "https://s.weibo.com/weibo?q=关晓彤王牌对王牌造型"
        },
        {
            "hot": "12万",
            "index": 37,
            "title": "陶喆大闹鲁豫有约2.0",
            "url": "https://s.weibo.com/weibo?q=陶喆大闹鲁豫有约2.0"
        },
        {
            "hot": "11万",
            "index": 38,
            "title": "丞磊好有梗一男的",
            "url": "https://s.weibo.com/weibo?q=丞磊好有梗一男的"
        },
        {
            "hot": "11万",
            "index": 39,
            "title": "一智障女子被男子带走失联",
            "url": "https://s.weibo.com/weibo?q=一智障女子被男子带走失联"
        },
        {
            "hot": "11万",
            "index": 40,
            "title": "李兰迪 喀什的风教我跳了一支舞",
            "url": "https://s.weibo.com/weibo?q=李兰迪 喀什的风教我跳了一支舞"
        },
        {
            "hot": "10万",
            "index": 41,
            "title": "浙D加长林肯趴窝合肥5年",
            "url": "https://s.weibo.com/weibo?q=浙D加长林肯趴窝合肥5年"
        },
        {
            "hot": "10万",
            "index": 42,
            "title": "泡泡玛特店员也吐槽迷你Labubu贵",
            "url": "https://s.weibo.com/weibo?q=泡泡玛特店员也吐槽迷你Labubu贵"
        },
        {
            "hot": "10万",
            "index": 43,
            "title": "伞兵暗夜王子",
            "url": "https://s.weibo.com/weibo?q=伞兵暗夜王子"
        },
        {
            "hot": "10万",
            "index": 44,
            "title": "保剑锋点外卖都写司马焦",
            "url": "https://s.weibo.com/weibo?q=保剑锋点外卖都写司马焦"
        },
        {
            "hot": "10万",
            "index": 45,
            "title": "A股高位股午后持续下挫",
            "url": "https://s.weibo.com/weibo?q=A股高位股午后持续下挫"
        },
        {
            "hot": "9万",
            "index": 46,
            "title": "两女子花3万请24位陪爬登顶泰山",
            "url": "https://s.weibo.com/weibo?q=两女子花3万请24位陪爬登顶泰山"
        },
        {
            "hot": "9万",
            "index": 47,
            "title": "蓝盈莹红裙子红玫瑰",
            "url": "https://s.weibo.com/weibo?q=蓝盈莹红裙子红玫瑰"
        },
        {
            "hot": "9万",
            "index": 48,
            "title": "敦促日方深刻反省侵略历史",
            "url": "https://s.weibo.com/weibo?q=敦促日方深刻反省侵略历史"
        },
        {
            "hot": "9万",
            "index": 49,
            "title": "王安宇男友风",
            "url": "https://s.weibo.com/weibo?q=王安宇男友风"
        },
        {
            "hot": "9万",
            "index": 50,
            "title": "反诈老陈又翻车了",
            "url": "https://s.weibo.com/weibo?q=反诈老陈又翻车了"
        },
        {
            "hot": "9万",
            "index": 51,
            "title": "日本博主在网络上离间中国民众",
            "url": "https://s.weibo.com/weibo?q=日本博主在网络上离间中国民众"
        },
        {
            "hot": "9万",
            "index": 52,
            "title": "侄子在网上买了一份六手网课",
            "url": "https://s.weibo.com/weibo?q=侄子在网上买了一份六手网课"
        }
    ],
    "request_id": "8fb4e802d2b39ee63f918da1"
}