{
    "code": 200,
    "msg": "数据请求成功",
    "data": [
        {
            "hot": "111万",
            "index": 1,
            "title": "火箭军倒查9年揪出采购掮客",
            "url": "https://s.weibo.com/weibo?q=火箭军倒查9年揪出采购掮客"
        },
        {
            "hot": "44万",
            "index": 2,
            "title": "花中国的钱插刀中国绝不容忍",
            "url": "https://s.weibo.com/weibo?q=花中国的钱插刀中国绝不容忍"
        },
        {
            "hot": "41万",
            "index": 3,
            "title": "当网警遇上教师节他们是别样的教师",
            "url": "https://s.weibo.com/weibo?q=当网警遇上教师节他们是别样的教师"
        },
        {
            "hot": "41万",
            "index": 4,
            "title": "新一代智己LS6震撼上市",
            "url": "https://s.weibo.com/weibo?q=新一代智己LS6震撼上市"
        },
        {
            "hot": "41万",
            "index": 5,
            "title": "花2000万买房又花188万买家装包",
            "url": "https://s.weibo.com/weibo?q=花2000万买房又花188万买家装包"
        },
        {
            "hot": "39万",
            "index": 6,
            "title": "男子高铁座位上旁若无人抽烟",
            "url": "https://s.weibo.com/weibo?q=男子高铁座位上旁若无人抽烟"
        },
        {
            "hot": "36万",
            "index": 7,
            "title": "韩国iPhoneAir没有捏合手势",
            "url": "https://s.weibo.com/weibo?q=韩国iPhoneAir没有捏合手势"
        },
        {
            "hot": "33万",
            "index": 8,
            "title": "老师请答题",
            "url": "https://s.weibo.com/weibo?q=老师请答题"
        },
        {
            "hot": "33万",
            "index": 9,
            "title": "中国空军运20接30名烈士回家",
            "url": "https://s.weibo.com/weibo?q=中国空军运20接30名烈士回家"
        },
        {
            "hot": "31万",
            "index": 10,
            "title": "网红柴怼怼被警方带走调查",
            "url": "https://s.weibo.com/weibo?q=网红柴怼怼被警方带走调查"
        },
        {
            "hot": "30万",
            "index": 11,
            "title": "日本民众喊话石平滚出日本",
            "url": "https://s.weibo.com/weibo?q=日本民众喊话石平滚出日本"
        },
        {
            "hot": "30万",
            "index": 12,
            "title": "警方回应文昌阁小猫遭挖眼砍断四肢",
            "url": "https://s.weibo.com/weibo?q=警方回应文昌阁小猫遭挖眼砍断四肢"
        },
        {
            "hot": "30万",
            "index": 13,
            "title": "祝绪丹手滑",
            "url": "https://s.weibo.com/weibo?q=祝绪丹手滑"
        },
        {
            "hot": "30万",
            "index": 14,
            "title": "那英老公回应",
            "url": "https://s.weibo.com/weibo?q=那英老公回应"
        },
        {
            "hot": "30万",
            "index": 15,
            "title": "辛芷蕾手机要爆炸了",
            "url": "https://s.weibo.com/weibo?q=辛芷蕾手机要爆炸了"
        },
        {
            "hot": "30万",
            "index": 16,
            "title": "豆沙馅真的塌房了",
            "url": "https://s.weibo.com/weibo?q=豆沙馅真的塌房了"
        },
        {
            "hot": "30万",
            "index": 17,
            "title": "iPhone16背刺最大一代",
            "url": "https://s.weibo.com/weibo?q=iPhone16背刺最大一代"
        },
        {
            "hot": "30万",
            "index": 18,
            "title": "管乐疑似把粉丝送的礼物送给相亲对象",
            "url": "https://s.weibo.com/weibo?q=管乐疑似把粉丝送的礼物送给相亲对象"
        },
        {
            "hot": "30万",
            "index": 19,
            "title": "一年了我的互联网孩子回归了",
            "url": "https://s.weibo.com/weibo?q=一年了我的互联网孩子回归了"
        },
        {
            "hot": "29万",
            "index": 20,
            "title": "花少7真的把马思纯养的很好",
            "url": "https://s.weibo.com/weibo?q=花少7真的把马思纯养的很好"
        },
        {
            "hot": "29万",
            "index": 21,
            "title": "别人扫楼王鹤棣官宣扫街",
            "url": "https://s.weibo.com/weibo?q=别人扫楼王鹤棣官宣扫街"
        },
        {
            "hot": "29万",
            "index": 22,
            "title": "合租房生娃夫妻未认可退租搬家方案",
            "url": "https://s.weibo.com/weibo?q=合租房生娃夫妻未认可退租搬家方案"
        },
        {
            "hot": "29万",
            "index": 23,
            "title": "娜扎把杨幂编辑掉了",
            "url": "https://s.weibo.com/weibo?q=娜扎把杨幂编辑掉了"
        },
        {
            "hot": "29万",
            "index": 24,
            "title": "高德每天为线下店多带1000万消费者",
            "url": "https://s.weibo.com/weibo?q=高德每天为线下店多带1000万消费者"
        },
        {
            "hot": "29万",
            "index": 25,
            "title": "传统点评榜单不该是餐饮指挥棒",
            "url": "https://s.weibo.com/weibo?q=传统点评榜单不该是餐饮指挥棒"
        },
        {
            "hot": "29万",
            "index": 26,
            "title": "赵磊上婚综是为了正式介绍太太",
            "url": "https://s.weibo.com/weibo?q=赵磊上婚综是为了正式介绍太太"
        },
        {
            "hot": "29万",
            "index": 27,
            "title": "成毅新剧一胎三胞",
            "url": "https://s.weibo.com/weibo?q=成毅新剧一胎三胞"
        },
        {
            "hot": "29万",
            "index": 28,
            "title": "武艺为了付辛博快点结婚吧",
            "url": "https://s.weibo.com/weibo?q=武艺为了付辛博快点结婚吧"
        },
        {
            "hot": "28万",
            "index": 29,
            "title": "吴奇隆 我的祖籍是福建泉州",
            "url": "https://s.weibo.com/weibo?q=吴奇隆 我的祖籍是福建泉州"
        },
        {
            "hot": "28万",
            "index": 30,
            "title": "高德推出全球首个用脚投票美食榜",
            "url": "https://s.weibo.com/weibo?q=高德推出全球首个用脚投票美食榜"
        },
        {
            "hot": "28万",
            "index": 31,
            "title": "高德扫街榜给传统美食榜挤水分",
            "url": "https://s.weibo.com/weibo?q=高德扫街榜给传统美食榜挤水分"
        },
        {
            "hot": "28万",
            "index": 32,
            "title": "民警回应柴怼怼被立案调查",
            "url": "https://s.weibo.com/weibo?q=民警回应柴怼怼被立案调查"
        },
        {
            "hot": "28万",
            "index": 33,
            "title": "部分人买iPhone竟然因其保值",
            "url": "https://s.weibo.com/weibo?q=部分人买iPhone竟然因其保值"
        },
        {
            "hot": "28万",
            "index": 34,
            "title": "那英在英国陪女儿读书",
            "url": "https://s.weibo.com/weibo?q=那英在英国陪女儿读书"
        },
        {
            "hot": "28万",
            "index": 35,
            "title": "巩俐周迅赵丽颖倪妮祝贺辛芷蕾",
            "url": "https://s.weibo.com/weibo?q=巩俐周迅赵丽颖倪妮祝贺辛芷蕾"
        },
        {
            "hot": "28万",
            "index": 36,
            "title": "洗澡三小时 客户被盘了一个半小时",
            "url": "https://s.weibo.com/weibo?q=洗澡三小时 客户被盘了一个半小时"
        },
        {
            "hot": "28万",
            "index": 37,
            "title": "pdf不行 得PDF才行",
            "url": "https://s.weibo.com/weibo?q=pdf不行 得PDF才行"
        },
        {
            "hot": "26万",
            "index": 38,
            "title": "黄景瑜前妻 俩孩子一个被他打没了",
            "url": "https://s.weibo.com/weibo?q=黄景瑜前妻 俩孩子一个被他打没了"
        },
        {
            "hot": "23万",
            "index": 39,
            "title": "iPhone17",
            "url": "https://s.weibo.com/weibo?q=iPhone17"
        },
        {
            "hot": "23万",
            "index": 40,
            "title": "河北一女子骑车路上被狗撞倒身亡",
            "url": "https://s.weibo.com/weibo?q=河北一女子骑车路上被狗撞倒身亡"
        },
        {
            "hot": "23万",
            "index": 41,
            "title": "游客拍骆驼挨打被要求删视频",
            "url": "https://s.weibo.com/weibo?q=游客拍骆驼挨打被要求删视频"
        },
        {
            "hot": "22万",
            "index": 42,
            "title": "00后教师们的活人感有多强",
            "url": "https://s.weibo.com/weibo?q=00后教师们的活人感有多强"
        },
        {
            "hot": "22万",
            "index": 43,
            "title": "张艺兴张艺谋合照",
            "url": "https://s.weibo.com/weibo?q=张艺兴张艺谋合照"
        },
        {
            "hot": "22万",
            "index": 44,
            "title": "苹果韩国官网 没有手",
            "url": "https://s.weibo.com/weibo?q=苹果韩国官网 没有手"
        },
        {
            "hot": "17万",
            "index": 45,
            "title": "12306回应男子高铁抽烟被民警带走",
            "url": "https://s.weibo.com/weibo?q=12306回应男子高铁抽烟被民警带走"
        },
        {
            "hot": "16万",
            "index": 46,
            "title": "花30万娶的老婆一个月不到跑了",
            "url": "https://s.weibo.com/weibo?q=花30万娶的老婆一个月不到跑了"
        },
        {
            "hot": "16万",
            "index": 47,
            "title": "iPhone17ProMax离谱手机壳",
            "url": "https://s.weibo.com/weibo?q=iPhone17ProMax离谱手机壳"
        },
        {
            "hot": "16万",
            "index": 48,
            "title": "大黄胡楚靓 远离low货",
            "url": "https://s.weibo.com/weibo?q=大黄胡楚靓 远离low货"
        },
        {
            "hot": "13万",
            "index": 49,
            "title": "A股成交跌破2万亿",
            "url": "https://s.weibo.com/weibo?q=A股成交跌破2万亿"
        },
        {
            "hot": "13万",
            "index": 50,
            "title": "iPhone17 关闭摇一摇广告",
            "url": "https://s.weibo.com/weibo?q=iPhone17 关闭摇一摇广告"
        },
        {
            "hot": "13万",
            "index": 51,
            "title": "管乐回应粉丝",
            "url": "https://s.weibo.com/weibo?q=管乐回应粉丝"
        },
        {
            "hot": "13万",
            "index": 52,
            "title": "月经3天干净和7天干净都一样",
            "url": "https://s.weibo.com/weibo?q=月经3天干净和7天干净都一样"
        }
    ],
    "request_id": "61bde6ca59407cfcd7becfad"
}