{
    "code": 200,
    "msg": "数据请求成功",
    "data": [
        {
            "hot": "1151万",
            "index": 1,
            "title": "桦加沙",
            "url": "https://s.weibo.com/weibo?q=桦加沙"
        },
        {
            "hot": "113万",
            "index": 2,
            "title": "桦加沙登陆地点确认",
            "url": "https://s.weibo.com/weibo?q=桦加沙登陆地点确认"
        },
        {
            "hot": "53万",
            "index": 3,
            "title": "致敬耕耘礼赞丰收",
            "url": "https://s.weibo.com/weibo?q=致敬耕耘礼赞丰收"
        },
        {
            "hot": "40万",
            "index": 4,
            "title": "香港台风",
            "url": "https://s.weibo.com/weibo?q=香港台风"
        },
        {
            "hot": "34万",
            "index": 5,
            "title": "桦加沙路径",
            "url": "https://s.weibo.com/weibo?q=桦加沙路径"
        },
        {
            "hot": "34万",
            "index": 6,
            "title": "妈妈回应瑶一瑶小肉包颜值状态",
            "url": "https://s.weibo.com/weibo?q=妈妈回应瑶一瑶小肉包颜值状态"
        },
        {
            "hot": "34万",
            "index": 7,
            "title": "全村的希望开挖了",
            "url": "https://s.weibo.com/weibo?q=全村的希望开挖了"
        },
        {
            "hot": "33万",
            "index": 8,
            "title": "广州全市五停",
            "url": "https://s.weibo.com/weibo?q=广州全市五停"
        },
        {
            "hot": "25万",
            "index": 9,
            "title": "MAMA票价",
            "url": "https://s.weibo.com/weibo?q=MAMA票价"
        },
        {
            "hot": "23万",
            "index": 10,
            "title": "金鸡奖提名名单预测",
            "url": "https://s.weibo.com/weibo?q=金鸡奖提名名单预测"
        },
        {
            "hot": "23万",
            "index": 11,
            "title": "深圳不语只是一味提前砍树",
            "url": "https://s.weibo.com/weibo?q=深圳不语只是一味提前砍树"
        },
        {
            "hot": "23万",
            "index": 12,
            "title": "台风前夕腾讯把企鹅拴住了",
            "url": "https://s.weibo.com/weibo?q=台风前夕腾讯把企鹅拴住了"
        },
        {
            "hot": "23万",
            "index": 13,
            "title": "28岁男子上树被自带绳子缠脖身亡",
            "url": "https://s.weibo.com/weibo?q=28岁男子上树被自带绳子缠脖身亡"
        },
        {
            "hot": "22万",
            "index": 14,
            "title": "男子嫖娼前猝死家属索赔卖淫女131万",
            "url": "https://s.weibo.com/weibo?q=男子嫖娼前猝死家属索赔卖淫女131万"
        },
        {
            "hot": "22万",
            "index": 15,
            "title": "中国游客腹痛日本医生见死不救",
            "url": "https://s.weibo.com/weibo?q=中国游客腹痛日本医生见死不救"
        },
        {
            "hot": "22万",
            "index": 16,
            "title": "煮鸡蛋忘了关火后诞生的艺术作品",
            "url": "https://s.weibo.com/weibo?q=煮鸡蛋忘了关火后诞生的艺术作品"
        },
        {
            "hot": "20万",
            "index": 17,
            "title": "王俊凯高干文男主",
            "url": "https://s.weibo.com/weibo?q=王俊凯高干文男主"
        },
        {
            "hot": "19万",
            "index": 18,
            "title": "桦加沙强度",
            "url": "https://s.weibo.com/weibo?q=桦加沙强度"
        },
        {
            "hot": "17万",
            "index": 19,
            "title": "福地怀化湘当懂你",
            "url": "https://s.weibo.com/weibo?q=福地怀化湘当懂你"
        },
        {
            "hot": "17万",
            "index": 20,
            "title": "广州地铁",
            "url": "https://s.weibo.com/weibo?q=广州地铁"
        },
        {
            "hot": "17万",
            "index": 21,
            "title": "许光汉瘦回来了",
            "url": "https://s.weibo.com/weibo?q=许光汉瘦回来了"
        },
        {
            "hot": "17万",
            "index": 22,
            "title": "韦雪回应9亿分手费",
            "url": "https://s.weibo.com/weibo?q=韦雪回应9亿分手费"
        },
        {
            "hot": "17万",
            "index": 23,
            "title": "李一桐被磕掉了一颗牙",
            "url": "https://s.weibo.com/weibo?q=李一桐被磕掉了一颗牙"
        },
        {
            "hot": "17万",
            "index": 24,
            "title": "宋轶怎么美成这样了",
            "url": "https://s.weibo.com/weibo?q=宋轶怎么美成这样了"
        },
        {
            "hot": "16万",
            "index": 25,
            "title": "乔欣变美了",
            "url": "https://s.weibo.com/weibo?q=乔欣变美了"
        },
        {
            "hot": "16万",
            "index": 26,
            "title": "南京地下室被猜测凶宅房主报警",
            "url": "https://s.weibo.com/weibo?q=南京地下室被猜测凶宅房主报警"
        },
        {
            "hot": "15万",
            "index": 27,
            "title": "痴情的火鸡面啊再等一世吧",
            "url": "https://s.weibo.com/weibo?q=痴情的火鸡面啊再等一世吧"
        },
        {
            "hot": "15万",
            "index": 28,
            "title": "李在明声称中俄朝走近我们很难做",
            "url": "https://s.weibo.com/weibo?q=李在明声称中俄朝走近我们很难做"
        },
        {
            "hot": "14万",
            "index": 29,
            "title": "中国每年吃掉约70亿只白羽肉鸡",
            "url": "https://s.weibo.com/weibo?q=中国每年吃掉约70亿只白羽肉鸡"
        },
        {
            "hot": "14万",
            "index": 30,
            "title": "Angelababy秋日蜜糖妆",
            "url": "https://s.weibo.com/weibo?q=Angelababy秋日蜜糖妆"
        },
        {
            "hot": "14万",
            "index": 31,
            "title": "长安二十四计",
            "url": "https://s.weibo.com/weibo?q=长安二十四计"
        },
        {
            "hot": "14万",
            "index": 32,
            "title": "敷尔佳给赴尔摩斯的快乐谁懂",
            "url": "https://s.weibo.com/weibo?q=敷尔佳给赴尔摩斯的快乐谁懂"
        },
        {
            "hot": "14万",
            "index": 33,
            "title": "香港一家三口被巨浪卷走",
            "url": "https://s.weibo.com/weibo?q=香港一家三口被巨浪卷走"
        },
        {
            "hot": "13万",
            "index": 34,
            "title": "时代少年团一起为刘耀文庆生",
            "url": "https://s.weibo.com/weibo?q=时代少年团一起为刘耀文庆生"
        },
        {
            "hot": "13万",
            "index": 35,
            "title": "好友曝何猷启恋情",
            "url": "https://s.weibo.com/weibo?q=好友曝何猷启恋情"
        },
        {
            "hot": "13万",
            "index": 36,
            "title": "方媛挺孕肚工作",
            "url": "https://s.weibo.com/weibo?q=方媛挺孕肚工作"
        },
        {
            "hot": "13万",
            "index": 37,
            "title": "广东或遇人类最大台风灾害系谣言",
            "url": "https://s.weibo.com/weibo?q=广东或遇人类最大台风灾害系谣言"
        },
        {
            "hot": "12万",
            "index": 38,
            "title": "因买不起房一家四口开房车旅居近2年",
            "url": "https://s.weibo.com/weibo?q=因买不起房一家四口开房车旅居近2年"
        },
        {
            "hot": "12万",
            "index": 39,
            "title": "赵让男主戏唯一资方",
            "url": "https://s.weibo.com/weibo?q=赵让男主戏唯一资方"
        },
        {
            "hot": "12万",
            "index": 40,
            "title": "广州伤医事件",
            "url": "https://s.weibo.com/weibo?q=广州伤医事件"
        },
        {
            "hot": "12万",
            "index": 41,
            "title": "瘦47斤发现不止身材变了",
            "url": "https://s.weibo.com/weibo?q=瘦47斤发现不止身材变了"
        },
        {
            "hot": "12万",
            "index": 42,
            "title": "雎晓雯把冲锋衣穿出高定感",
            "url": "https://s.weibo.com/weibo?q=雎晓雯把冲锋衣穿出高定感"
        },
        {
            "hot": "11万",
            "index": 43,
            "title": "医院影像科报告单出现骂人脏话",
            "url": "https://s.weibo.com/weibo?q=医院影像科报告单出现骂人脏话"
        },
        {
            "hot": "11万",
            "index": 44,
            "title": "专家称桦加沙强度临地球上限不科学",
            "url": "https://s.weibo.com/weibo?q=专家称桦加沙强度临地球上限不科学"
        },
        {
            "hot": "11万",
            "index": 45,
            "title": "女子术后20天发现体内留纱布已发臭",
            "url": "https://s.weibo.com/weibo?q=女子术后20天发现体内留纱布已发臭"
        },
        {
            "hot": "10万",
            "index": 46,
            "title": "名侦探柯南演都不演了",
            "url": "https://s.weibo.com/weibo?q=名侦探柯南演都不演了"
        },
        {
            "hot": "10万",
            "index": 47,
            "title": "台风 广东病",
            "url": "https://s.weibo.com/weibo?q=台风 广东病"
        },
        {
            "hot": "10万",
            "index": 48,
            "title": "腾讯回应拴Q",
            "url": "https://s.weibo.com/weibo?q=腾讯回应拴Q"
        },
        {
            "hot": "10万",
            "index": 49,
            "title": "李想称iPhone17ProMax太丑",
            "url": "https://s.weibo.com/weibo?q=李想称iPhone17ProMax太丑"
        },
        {
            "hot": "9万",
            "index": 50,
            "title": "直播卖烤肠女子又遇城管",
            "url": "https://s.weibo.com/weibo?q=直播卖烤肠女子又遇城管"
        },
        {
            "hot": "9万",
            "index": 51,
            "title": "23日夜间深圳风雨最强",
            "url": "https://s.weibo.com/weibo?q=23日夜间深圳风雨最强"
        }
    ],
    "request_id": "26f353dbb58cced3563bb898"
}