{
    "code": 200,
    "msg": "数据请求成功",
    "data": [
        {
            "hot": "108万",
            "index": 1,
            "title": "导致视力下降的真实原因",
            "url": "https://s.weibo.com/weibo?q=导致视力下降的真实原因"
        },
        {
            "hot": "30万",
            "index": 2,
            "title": "章莹颖男友协助章父直播回应新恋情",
            "url": "https://s.weibo.com/weibo?q=章莹颖男友协助章父直播回应新恋情"
        },
        {
            "hot": "26万",
            "index": 3,
            "title": "国庆中秋假期游玩好去处",
            "url": "https://s.weibo.com/weibo?q=国庆中秋假期游玩好去处"
        },
        {
            "hot": "23万",
            "index": 4,
            "title": "泰山山顶宾馆提供99元坐席可过夜",
            "url": "https://s.weibo.com/weibo?q=泰山山顶宾馆提供99元坐席可过夜"
        },
        {
            "hot": "21万",
            "index": 5,
            "title": "人人人人人人鸡排哥人人人人人人",
            "url": "https://s.weibo.com/weibo?q=人人人人人人鸡排哥人人人人人人"
        },
        {
            "hot": "17万",
            "index": 6,
            "title": "王楚钦卡壳半天蹦出来一句他老婆",
            "url": "https://s.weibo.com/weibo?q=王楚钦卡壳半天蹦出来一句他老婆"
        },
        {
            "hot": "16万",
            "index": 7,
            "title": "罗意威2026春夏女装秀",
            "url": "https://s.weibo.com/weibo?q=罗意威2026春夏女装秀"
        },
        {
            "hot": "15万",
            "index": 8,
            "title": "女子电话得知车被狗啃以为是诈骗",
            "url": "https://s.weibo.com/weibo?q=女子电话得知车被狗啃以为是诈骗"
        },
        {
            "hot": "15万",
            "index": 9,
            "title": "陈泽",
            "url": "https://s.weibo.com/weibo?q=陈泽"
        },
        {
            "hot": "10万",
            "index": 10,
            "title": "香港人盯上内地医保",
            "url": "https://s.weibo.com/weibo?q=香港人盯上内地医保"
        },
        {
            "hot": "9万",
            "index": 11,
            "title": "运动三个月不胖和好瘦的区别",
            "url": "https://s.weibo.com/weibo?q=运动三个月不胖和好瘦的区别"
        },
        {
            "hot": "9万",
            "index": 12,
            "title": "章莹颖男友已开始新恋情",
            "url": "https://s.weibo.com/weibo?q=章莹颖男友已开始新恋情"
        },
        {
            "hot": "9万",
            "index": 13,
            "title": "陈赫一家四口瑞士度假",
            "url": "https://s.weibo.com/weibo?q=陈赫一家四口瑞士度假"
        },
        {
            "hot": "9万",
            "index": 14,
            "title": "许妍卸妆",
            "url": "https://s.weibo.com/weibo?q=许妍卸妆"
        },
        {
            "hot": "9万",
            "index": 15,
            "title": "李纯马頔回复王菊",
            "url": "https://s.weibo.com/weibo?q=李纯马頔回复王菊"
        },
        {
            "hot": "9万",
            "index": 16,
            "title": "女兵写请战书驾驶歼16",
            "url": "https://s.weibo.com/weibo?q=女兵写请战书驾驶歼16"
        },
        {
            "hot": "9万",
            "index": 17,
            "title": "在中国居住了5年的印度女子",
            "url": "https://s.weibo.com/weibo?q=在中国居住了5年的印度女子"
        },
        {
            "hot": "9万",
            "index": 18,
            "title": "泰国男子找回手机相册惊现尸骨照",
            "url": "https://s.weibo.com/weibo?q=泰国男子找回手机相册惊现尸骨照"
        },
        {
            "hot": "9万",
            "index": 19,
            "title": "英皇欠钱的最大受益人",
            "url": "https://s.weibo.com/weibo?q=英皇欠钱的最大受益人"
        },
        {
            "hot": "9万",
            "index": 20,
            "title": "迪丽热巴ins",
            "url": "https://s.weibo.com/weibo?q=迪丽热巴ins"
        },
        {
            "hot": "9万",
            "index": 21,
            "title": "成龙王力宏亲了",
            "url": "https://s.weibo.com/weibo?q=成龙王力宏亲了"
        },
        {
            "hot": "9万",
            "index": 22,
            "title": "导演看了花少5才选择了王安宇",
            "url": "https://s.weibo.com/weibo?q=导演看了花少5才选择了王安宇"
        },
        {
            "hot": "9万",
            "index": 23,
            "title": "印度妇女用纱丽掩人耳目偷走金项链",
            "url": "https://s.weibo.com/weibo?q=印度妇女用纱丽掩人耳目偷走金项链"
        },
        {
            "hot": "9万",
            "index": 24,
            "title": "对沈佳润是小孩有了实感",
            "url": "https://s.weibo.com/weibo?q=对沈佳润是小孩有了实感"
        },
        {
            "hot": "9万",
            "index": 25,
            "title": "一款外军战机被赶走再没回来过",
            "url": "https://s.weibo.com/weibo?q=一款外军战机被赶走再没回来过"
        },
        {
            "hot": "9万",
            "index": 26,
            "title": "东北虎二埋汰穿西装迎客",
            "url": "https://s.weibo.com/weibo?q=东北虎二埋汰穿西装迎客"
        },
        {
            "hot": "8万",
            "index": 27,
            "title": "双休7千单休9千怎么选",
            "url": "https://s.weibo.com/weibo?q=双休7千单休9千怎么选"
        },
        {
            "hot": "8万",
            "index": 28,
            "title": "大连地铁发生意外故障停运一小时",
            "url": "https://s.weibo.com/weibo?q=大连地铁发生意外故障停运一小时"
        },
        {
            "hot": "7万",
            "index": 29,
            "title": "多位名人自曝戴呼吸机睡觉",
            "url": "https://s.weibo.com/weibo?q=多位名人自曝戴呼吸机睡觉"
        },
        {
            "hot": "7万",
            "index": 30,
            "title": "一晚上偶遇三次鹿晗",
            "url": "https://s.weibo.com/weibo?q=一晚上偶遇三次鹿晗"
        },
        {
            "hot": "7万",
            "index": 31,
            "title": "我驻韩使馆就反华游行表明严正立场",
            "url": "https://s.weibo.com/weibo?q=我驻韩使馆就反华游行表明严正立场"
        },
        {
            "hot": "7万",
            "index": 32,
            "title": "智能马桶喷出开水女子被烫伤",
            "url": "https://s.weibo.com/weibo?q=智能马桶喷出开水女子被烫伤"
        },
        {
            "hot": "6万",
            "index": 33,
            "title": "王俊凯小说男主身材比例",
            "url": "https://s.weibo.com/weibo?q=王俊凯小说男主身材比例"
        },
        {
            "hot": "6万",
            "index": 34,
            "title": "女子假期外出3C充电宝在家自爆",
            "url": "https://s.weibo.com/weibo?q=女子假期外出3C充电宝在家自爆"
        },
        {
            "hot": "5万",
            "index": 35,
            "title": "特斯拉汉堡销量碾压麦当劳",
            "url": "https://s.weibo.com/weibo?q=特斯拉汉堡销量碾压麦当劳"
        },
        {
            "hot": "5万",
            "index": 36,
            "title": "许我耀眼腾讯热度破32000",
            "url": "https://s.weibo.com/weibo?q=许我耀眼腾讯热度破32000"
        },
        {
            "hot": "5万",
            "index": 37,
            "title": "于适稳稳地帮六公主完美救场",
            "url": "https://s.weibo.com/weibo?q=于适稳稳地帮六公主完美救场"
        },
        {
            "hot": "5万",
            "index": 38,
            "title": "提醒在韩中国游客注意人身安全",
            "url": "https://s.weibo.com/weibo?q=提醒在韩中国游客注意人身安全"
        },
        {
            "hot": "5万",
            "index": 39,
            "title": "陈赫问张子萱需不需要打码",
            "url": "https://s.weibo.com/weibo?q=陈赫问张子萱需不需要打码"
        },
        {
            "hot": "5万",
            "index": 40,
            "title": "许魏洲被cpf贴脸",
            "url": "https://s.weibo.com/weibo?q=许魏洲被cpf贴脸"
        },
        {
            "hot": "5万",
            "index": 41,
            "title": "中国驻韩国大使馆严正发声",
            "url": "https://s.weibo.com/weibo?q=中国驻韩国大使馆严正发声"
        },
        {
            "hot": "4万",
            "index": 42,
            "title": "白宫裁员",
            "url": "https://s.weibo.com/weibo?q=白宫裁员"
        },
        {
            "hot": "4万",
            "index": 43,
            "title": "蔡徐坤国际认可度",
            "url": "https://s.weibo.com/weibo?q=蔡徐坤国际认可度"
        },
        {
            "hot": "4万",
            "index": 44,
            "title": "陈伟霆我二十来岁就跟着你了",
            "url": "https://s.weibo.com/weibo?q=陈伟霆我二十来岁就跟着你了"
        },
        {
            "hot": "4万",
            "index": 45,
            "title": "肖战唱完歌以为自己下班了",
            "url": "https://s.weibo.com/weibo?q=肖战唱完歌以为自己下班了"
        },
        {
            "hot": "4万",
            "index": 46,
            "title": "咪豆音乐节",
            "url": "https://s.weibo.com/weibo?q=咪豆音乐节"
        },
        {
            "hot": "4万",
            "index": 47,
            "title": "特朗普称若政府持续停摆可能会裁员",
            "url": "https://s.weibo.com/weibo?q=特朗普称若政府持续停摆可能会裁员"
        },
        {
            "hot": "4万",
            "index": 48,
            "title": "王楚钦回应与安宰贤搭档男双",
            "url": "https://s.weibo.com/weibo?q=王楚钦回应与安宰贤搭档男双"
        },
        {
            "hot": "4万",
            "index": 49,
            "title": "宋亚轩 敬山水",
            "url": "https://s.weibo.com/weibo?q=宋亚轩 敬山水"
        },
        {
            "hot": "4万",
            "index": 50,
            "title": "中方向美方明确提出四不",
            "url": "https://s.weibo.com/weibo?q=中方向美方明确提出四不"
        },
        {
            "hot": "4万",
            "index": 51,
            "title": "戚薇g社镜头",
            "url": "https://s.weibo.com/weibo?q=戚薇g社镜头"
        }
    ],
    "request_id": "19d2a19900b5531723f245f9"
}