{
    "code": 200,
    "msg": "数据请求成功",
    "data": [
        {
            "hot": "167万",
            "index": 1,
            "title": "小米16改名小米17",
            "url": "https://s.weibo.com/weibo?q=小米16改名小米17"
        },
        {
            "hot": "138万",
            "index": 2,
            "title": "支付宝账号解除授权",
            "url": "https://s.weibo.com/weibo?q=支付宝账号解除授权"
        },
        {
            "hot": "96万",
            "index": 3,
            "title": "丰收的田野是最美的画卷",
            "url": "https://s.weibo.com/weibo?q=丰收的田野是最美的画卷"
        },
        {
            "hot": "95万",
            "index": 4,
            "title": "蒙牛营养几代中国人的要强",
            "url": "https://s.weibo.com/weibo?q=蒙牛营养几代中国人的要强"
        },
        {
            "hot": "80万",
            "index": 5,
            "title": "奥运冠军邓琳琳官宣怀孕",
            "url": "https://s.weibo.com/weibo?q=奥运冠军邓琳琳官宣怀孕"
        },
        {
            "hot": "72万",
            "index": 6,
            "title": "小米17",
            "url": "https://s.weibo.com/weibo?q=小米17"
        },
        {
            "hot": "67万",
            "index": 7,
            "title": "Dior认领",
            "url": "https://s.weibo.com/weibo?q=Dior认领"
        },
        {
            "hot": "67万",
            "index": 8,
            "title": "网民造谣南阳法院警车接亲被行拘",
            "url": "https://s.weibo.com/weibo?q=网民造谣南阳法院警车接亲被行拘"
        },
        {
            "hot": "67万",
            "index": 9,
            "title": "贾玲开屏",
            "url": "https://s.weibo.com/weibo?q=贾玲开屏"
        },
        {
            "hot": "43万",
            "index": 10,
            "title": "租房新规今起实施",
            "url": "https://s.weibo.com/weibo?q=租房新规今起实施"
        },
        {
            "hot": "29万",
            "index": 11,
            "title": "中介发布假房源最高可罚10万元",
            "url": "https://s.weibo.com/weibo?q=中介发布假房源最高可罚10万元"
        },
        {
            "hot": "24万",
            "index": 12,
            "title": "骗子混入工作群冒充董事长骗走60万",
            "url": "https://s.weibo.com/weibo?q=骗子混入工作群冒充董事长骗走60万"
        },
        {
            "hot": "23万",
            "index": 13,
            "title": "罗永浩希望与贾国龙当面对话",
            "url": "https://s.weibo.com/weibo?q=罗永浩希望与贾国龙当面对话"
        },
        {
            "hot": "23万",
            "index": 14,
            "title": "宋妍霏回应提了24次裙子",
            "url": "https://s.weibo.com/weibo?q=宋妍霏回应提了24次裙子"
        },
        {
            "hot": "23万",
            "index": 15,
            "title": "网吧行业现状",
            "url": "https://s.weibo.com/weibo?q=网吧行业现状"
        },
        {
            "hot": "23万",
            "index": 16,
            "title": "iPhone17补贴后售价4999元",
            "url": "https://s.weibo.com/weibo?q=iPhone17补贴后售价4999元"
        },
        {
            "hot": "23万",
            "index": 17,
            "title": "731预告",
            "url": "https://s.weibo.com/weibo?q=731预告"
        },
        {
            "hot": "23万",
            "index": 18,
            "title": "汪苏泷演唱会",
            "url": "https://s.weibo.com/weibo?q=汪苏泷演唱会"
        },
        {
            "hot": "23万",
            "index": 19,
            "title": "wwd发了迪丽热巴刘雨昕",
            "url": "https://s.weibo.com/weibo?q=wwd发了迪丽热巴刘雨昕"
        },
        {
            "hot": "21万",
            "index": 20,
            "title": "韩国人街头高喊我们是柯克",
            "url": "https://s.weibo.com/weibo?q=韩国人街头高喊我们是柯克"
        },
        {
            "hot": "20万",
            "index": 21,
            "title": "孙颖莎澳门冠军赛卫冕发文",
            "url": "https://s.weibo.com/weibo?q=孙颖莎澳门冠军赛卫冕发文"
        },
        {
            "hot": "20万",
            "index": 22,
            "title": "卢伟冰称有信心直面iPhone17",
            "url": "https://s.weibo.com/weibo?q=卢伟冰称有信心直面iPhone17"
        },
        {
            "hot": "20万",
            "index": 23,
            "title": "国新办新闻发布会",
            "url": "https://s.weibo.com/weibo?q=国新办新闻发布会"
        },
        {
            "hot": "20万",
            "index": 24,
            "title": "你以为在备孕实际是避孕的行为",
            "url": "https://s.weibo.com/weibo?q=你以为在备孕实际是避孕的行为"
        },
        {
            "hot": "20万",
            "index": 25,
            "title": "农学生开学典礼能有多硬核",
            "url": "https://s.weibo.com/weibo?q=农学生开学典礼能有多硬核"
        },
        {
            "hot": "19万",
            "index": 26,
            "title": "周迅如懿传谣言澄清",
            "url": "https://s.weibo.com/weibo?q=周迅如懿传谣言澄清"
        },
        {
            "hot": "19万",
            "index": 27,
            "title": "731",
            "url": "https://s.weibo.com/weibo?q=731"
        },
        {
            "hot": "19万",
            "index": 28,
            "title": "叶舒华低马尾",
            "url": "https://s.weibo.com/weibo?q=叶舒华低马尾"
        },
        {
            "hot": "19万",
            "index": 29,
            "title": "震耳欲聋",
            "url": "https://s.weibo.com/weibo?q=震耳欲聋"
        },
        {
            "hot": "19万",
            "index": 30,
            "title": "艾美奖获奖名单",
            "url": "https://s.weibo.com/weibo?q=艾美奖获奖名单"
        },
        {
            "hot": "19万",
            "index": 31,
            "title": "张凌赫喜欢BE",
            "url": "https://s.weibo.com/weibo?q=张凌赫喜欢BE"
        },
        {
            "hot": "19万",
            "index": 32,
            "title": "租房新规实施这三点要注意",
            "url": "https://s.weibo.com/weibo?q=租房新规实施这三点要注意"
        },
        {
            "hot": "19万",
            "index": 33,
            "title": "外国醉汉殴打中国留学生",
            "url": "https://s.weibo.com/weibo?q=外国醉汉殴打中国留学生"
        },
        {
            "hot": "18万",
            "index": 34,
            "title": "小米17官宣本月发布",
            "url": "https://s.weibo.com/weibo?q=小米17官宣本月发布"
        },
        {
            "hot": "18万",
            "index": 35,
            "title": "瑞幸 星穹铁道",
            "url": "https://s.weibo.com/weibo?q=瑞幸 星穹铁道"
        },
        {
            "hot": "17万",
            "index": 36,
            "title": "BBC称日本从未正视侵略历史",
            "url": "https://s.weibo.com/weibo?q=BBC称日本从未正视侵略历史"
        },
        {
            "hot": "17万",
            "index": 37,
            "title": "李乃文又在哪闯什么祸呢",
            "url": "https://s.weibo.com/weibo?q=李乃文又在哪闯什么祸呢"
        },
        {
            "hot": "17万",
            "index": 38,
            "title": "妈妈亲手缝的NIKE书包火了",
            "url": "https://s.weibo.com/weibo?q=妈妈亲手缝的NIKE书包火了"
        },
        {
            "hot": "16万",
            "index": 39,
            "title": "甲状腺发出的求救信号",
            "url": "https://s.weibo.com/weibo?q=甲状腺发出的求救信号"
        },
        {
            "hot": "14万",
            "index": 40,
            "title": "A股",
            "url": "https://s.weibo.com/weibo?q=A股"
        },
        {
            "hot": "14万",
            "index": 41,
            "title": "张大奕聊名媛培训班",
            "url": "https://s.weibo.com/weibo?q=张大奕聊名媛培训班"
        },
        {
            "hot": "14万",
            "index": 42,
            "title": "付辛博不愧是初代选秀出来的",
            "url": "https://s.weibo.com/weibo?q=付辛博不愧是初代选秀出来的"
        },
        {
            "hot": "14万",
            "index": 43,
            "title": "8岁神经母细胞瘤患儿霖霖去世",
            "url": "https://s.weibo.com/weibo?q=8岁神经母细胞瘤患儿霖霖去世"
        },
        {
            "hot": "13万",
            "index": 44,
            "title": "王楚钦孙颖莎澳门城市宣传照",
            "url": "https://s.weibo.com/weibo?q=王楚钦孙颖莎澳门城市宣传照"
        },
        {
            "hot": "13万",
            "index": 45,
            "title": "孙颖莎说继续努力下个赛场见",
            "url": "https://s.weibo.com/weibo?q=孙颖莎说继续努力下个赛场见"
        },
        {
            "hot": "12万",
            "index": 46,
            "title": "这些租房糟心事有救了",
            "url": "https://s.weibo.com/weibo?q=这些租房糟心事有救了"
        },
        {
            "hot": "12万",
            "index": 47,
            "title": "ame",
            "url": "https://s.weibo.com/weibo?q=ame"
        },
        {
            "hot": "11万",
            "index": 48,
            "title": "加沙孩子要么饿死要么被炸死",
            "url": "https://s.weibo.com/weibo?q=加沙孩子要么饿死要么被炸死"
        },
        {
            "hot": "11万",
            "index": 49,
            "title": "iG 世界赛",
            "url": "https://s.weibo.com/weibo?q=iG 世界赛"
        },
        {
            "hot": "10万",
            "index": 50,
            "title": "花少这期直接升华了",
            "url": "https://s.weibo.com/weibo?q=花少这期直接升华了"
        },
        {
            "hot": "10万",
            "index": 51,
            "title": "王一博出道十一周年照",
            "url": "https://s.weibo.com/weibo?q=王一博出道十一周年照"
        },
        {
            "hot": "9万",
            "index": 52,
            "title": "宁德时代大涨逾6%",
            "url": "https://s.weibo.com/weibo?q=宁德时代大涨逾6%"
        }
    ],
    "request_id": "5a38ecb2f7642d8f976ee875"
}