{
    "code": 200,
    "msg": "数据请求成功",
    "data": [
        {
            "hot": "114万",
            "index": 1,
            "title": "甘肃一高校疑有女生校内分娩",
            "url": "https://s.weibo.com/weibo?q=甘肃一高校疑有女生校内分娩"
        },
        {
            "hot": "79万",
            "index": 2,
            "title": "阳光型抑郁",
            "url": "https://s.weibo.com/weibo?q=阳光型抑郁"
        },
        {
            "hot": "61万",
            "index": 3,
            "title": "一系列重要成果亮相2025年国家网络安全宣传周",
            "url": "https://s.weibo.com/weibo?q=一系列重要成果亮相2025年国家网络安全宣传周"
        },
        {
            "hot": "45万",
            "index": 4,
            "title": "广州大熊猫最便宜5块一只",
            "url": "https://s.weibo.com/weibo?q=广州大熊猫最便宜5块一只"
        },
        {
            "hot": "45万",
            "index": 5,
            "title": "赴山海制作方的力道用错了地方",
            "url": "https://s.weibo.com/weibo?q=赴山海制作方的力道用错了地方"
        },
        {
            "hot": "44万",
            "index": 6,
            "title": "男子查个税意外发现两份工资流水",
            "url": "https://s.weibo.com/weibo?q=男子查个税意外发现两份工资流水"
        },
        {
            "hot": "32万",
            "index": 7,
            "title": "男子在广东种出非洲猴面包树",
            "url": "https://s.weibo.com/weibo?q=男子在广东种出非洲猴面包树"
        },
        {
            "hot": "30万",
            "index": 8,
            "title": "山农大破解一科学界百年未解之谜",
            "url": "https://s.weibo.com/weibo?q=山农大破解一科学界百年未解之谜"
        },
        {
            "hot": "29万",
            "index": 9,
            "title": "2025国庆档电影",
            "url": "https://s.weibo.com/weibo?q=2025国庆档电影"
        },
        {
            "hot": "29万",
            "index": 10,
            "title": "秦始皇派人去昆仑采药是真的",
            "url": "https://s.weibo.com/weibo?q=秦始皇派人去昆仑采药是真的"
        },
        {
            "hot": "29万",
            "index": 11,
            "title": "涉毒艺人复出谁给开的绿灯",
            "url": "https://s.weibo.com/weibo?q=涉毒艺人复出谁给开的绿灯"
        },
        {
            "hot": "29万",
            "index": 12,
            "title": "关晓彤28岁生日照",
            "url": "https://s.weibo.com/weibo?q=关晓彤28岁生日照"
        },
        {
            "hot": "28万",
            "index": 13,
            "title": "00后女生追星频繁染发患肾病",
            "url": "https://s.weibo.com/weibo?q=00后女生追星频繁染发患肾病"
        },
        {
            "hot": "28万",
            "index": 14,
            "title": "重庆理工大学向学生致歉",
            "url": "https://s.weibo.com/weibo?q=重庆理工大学向学生致歉"
        },
        {
            "hot": "28万",
            "index": 15,
            "title": "哥哥用打火机电击洗澡妹妹致其烧伤",
            "url": "https://s.weibo.com/weibo?q=哥哥用打火机电击洗澡妹妹致其烧伤"
        },
        {
            "hot": "27万",
            "index": 16,
            "title": "加沙人问为何把孩子变成残肢断臂",
            "url": "https://s.weibo.com/weibo?q=加沙人问为何把孩子变成残肢断臂"
        },
        {
            "hot": "27万",
            "index": 17,
            "title": "警方通报一女子假扮骑手卖惨诈骗",
            "url": "https://s.weibo.com/weibo?q=警方通报一女子假扮骑手卖惨诈骗"
        },
        {
            "hot": "23万",
            "index": 18,
            "title": "于正虽然嘴碎但他护犊子啊",
            "url": "https://s.weibo.com/weibo?q=于正虽然嘴碎但他护犊子啊"
        },
        {
            "hot": "23万",
            "index": 19,
            "title": "奥斯卡回应恋综争议",
            "url": "https://s.weibo.com/weibo?q=奥斯卡回应恋综争议"
        },
        {
            "hot": "23万",
            "index": 20,
            "title": "生命树 纪录片",
            "url": "https://s.weibo.com/weibo?q=生命树 纪录片"
        },
        {
            "hot": "23万",
            "index": 21,
            "title": "日本拒绝美国",
            "url": "https://s.weibo.com/weibo?q=日本拒绝美国"
        },
        {
            "hot": "22万",
            "index": 22,
            "title": "预制了国庆八天的朋友圈",
            "url": "https://s.weibo.com/weibo?q=预制了国庆八天的朋友圈"
        },
        {
            "hot": "20万",
            "index": 23,
            "title": "终于知道为什么飞国外要提前3小时",
            "url": "https://s.weibo.com/weibo?q=终于知道为什么飞国外要提前3小时"
        },
        {
            "hot": "19万",
            "index": 24,
            "title": "汪苏泷36岁生日照",
            "url": "https://s.weibo.com/weibo?q=汪苏泷36岁生日照"
        },
        {
            "hot": "17万",
            "index": 25,
            "title": "90后女子背疼容易饿确诊胃癌晚期",
            "url": "https://s.weibo.com/weibo?q=90后女子背疼容易饿确诊胃癌晚期"
        },
        {
            "hot": "17万",
            "index": 26,
            "title": "原来真的有神兵天降",
            "url": "https://s.weibo.com/weibo?q=原来真的有神兵天降"
        },
        {
            "hot": "12万",
            "index": 27,
            "title": "晚睡晚起让人长期处于炎症状态",
            "url": "https://s.weibo.com/weibo?q=晚睡晚起让人长期处于炎症状态"
        },
        {
            "hot": "12万",
            "index": 28,
            "title": "迪卡侬广告 处女地",
            "url": "https://s.weibo.com/weibo?q=迪卡侬广告 处女地"
        },
        {
            "hot": "12万",
            "index": 29,
            "title": "刘翔的含金量还在上升",
            "url": "https://s.weibo.com/weibo?q=刘翔的含金量还在上升"
        },
        {
            "hot": "12万",
            "index": 30,
            "title": "白鹿为宋雨琦打call",
            "url": "https://s.weibo.com/weibo?q=白鹿为宋雨琦打call"
        },
        {
            "hot": "12万",
            "index": 31,
            "title": "多国呼吁中止以色列联合国会员国资格",
            "url": "https://s.weibo.com/weibo?q=多国呼吁中止以色列联合国会员国资格"
        },
        {
            "hot": "12万",
            "index": 32,
            "title": "无意识的控糖行为",
            "url": "https://s.weibo.com/weibo?q=无意识的控糖行为"
        },
        {
            "hot": "11万",
            "index": 33,
            "title": "深圳冷门兼职日薪2000元",
            "url": "https://s.weibo.com/weibo?q=深圳冷门兼职日薪2000元"
        },
        {
            "hot": "10万",
            "index": 34,
            "title": "柯克案嫌犯穿防自杀罩衣出庭",
            "url": "https://s.weibo.com/weibo?q=柯克案嫌犯穿防自杀罩衣出庭"
        },
        {
            "hot": "9万",
            "index": 35,
            "title": "鹿晗 邪恶银渐层",
            "url": "https://s.weibo.com/weibo?q=鹿晗 邪恶银渐层"
        },
        {
            "hot": "9万",
            "index": 36,
            "title": "陈星旭和妈妈共用一张脸",
            "url": "https://s.weibo.com/weibo?q=陈星旭和妈妈共用一张脸"
        },
        {
            "hot": "9万",
            "index": 37,
            "title": "难得夫妻是少年",
            "url": "https://s.weibo.com/weibo?q=难得夫妻是少年"
        },
        {
            "hot": "9万",
            "index": 38,
            "title": "AirPodsPro3加加班也没问题",
            "url": "https://s.weibo.com/weibo?q=AirPodsPro3加加班也没问题"
        },
        {
            "hot": "9万",
            "index": 39,
            "title": "易烊千玺 下播最快的主包",
            "url": "https://s.weibo.com/weibo?q=易烊千玺 下播最快的主包"
        },
        {
            "hot": "9万",
            "index": 40,
            "title": "女生坐火车卧铺打伞遮隐私",
            "url": "https://s.weibo.com/weibo?q=女生坐火车卧铺打伞遮隐私"
        },
        {
            "hot": "9万",
            "index": 41,
            "title": "可以二刷利剑玫瑰了",
            "url": "https://s.weibo.com/weibo?q=可以二刷利剑玫瑰了"
        },
        {
            "hot": "8万",
            "index": 42,
            "title": "外国小哥称明白中国为什么能领先了",
            "url": "https://s.weibo.com/weibo?q=外国小哥称明白中国为什么能领先了"
        },
        {
            "hot": "8万",
            "index": 43,
            "title": "易烊千玺微博直播",
            "url": "https://s.weibo.com/weibo?q=易烊千玺微博直播"
        },
        {
            "hot": "8万",
            "index": 44,
            "title": "特朗普访英引发民众抗议",
            "url": "https://s.weibo.com/weibo?q=特朗普访英引发民众抗议"
        },
        {
            "hot": "8万",
            "index": 45,
            "title": "闫妮晒照为关晓彤庆生",
            "url": "https://s.weibo.com/weibo?q=闫妮晒照为关晓彤庆生"
        },
        {
            "hot": "8万",
            "index": 46,
            "title": "单身不是最爽的",
            "url": "https://s.weibo.com/weibo?q=单身不是最爽的"
        },
        {
            "hot": "8万",
            "index": 47,
            "title": "iOS26解锁Siri五项新技能",
            "url": "https://s.weibo.com/weibo?q=iOS26解锁Siri五项新技能"
        },
        {
            "hot": "8万",
            "index": 48,
            "title": "仁川海警也许不用牺牲",
            "url": "https://s.weibo.com/weibo?q=仁川海警也许不用牺牲"
        },
        {
            "hot": "8万",
            "index": 49,
            "title": "这么会穿回头率一定很高吧",
            "url": "https://s.weibo.com/weibo?q=这么会穿回头率一定很高吧"
        },
        {
            "hot": "7万",
            "index": 50,
            "title": "731",
            "url": "https://s.weibo.com/weibo?q=731"
        }
    ],
    "request_id": "78da2e8d261db7741d5f4de9"
}