{
    "code": 200,
    "msg": "数据请求成功",
    "data": [
        {
            "hot": "873万",
            "index": 1,
            "title": "桦加沙",
            "url": "https://s.weibo.com/weibo?q=桦加沙"
        },
        {
            "hot": "119万",
            "index": 2,
            "title": "盒马回应最难吃甜品被台风选出来了",
            "url": "https://s.weibo.com/weibo?q=盒马回应最难吃甜品被台风选出来了"
        },
        {
            "hot": "104万",
            "index": 3,
            "title": "从田间到指尖的丰收路",
            "url": "https://s.weibo.com/weibo?q=从田间到指尖的丰收路"
        },
        {
            "hot": "101万",
            "index": 4,
            "title": "秋日养出润透发光肌",
            "url": "https://s.weibo.com/weibo?q=秋日养出润透发光肌"
        },
        {
            "hot": "94万",
            "index": 5,
            "title": "香港一家三口被巨浪卷走",
            "url": "https://s.weibo.com/weibo?q=香港一家三口被巨浪卷走"
        },
        {
            "hot": "78万",
            "index": 6,
            "title": "朝雪录",
            "url": "https://s.weibo.com/weibo?q=朝雪录"
        },
        {
            "hot": "74万",
            "index": 7,
            "title": "王晓晨否认结婚",
            "url": "https://s.weibo.com/weibo?q=王晓晨否认结婚"
        },
        {
            "hot": "70万",
            "index": 8,
            "title": "开学搞点食力装备",
            "url": "https://s.weibo.com/weibo?q=开学搞点食力装备"
        },
        {
            "hot": "53万",
            "index": 9,
            "title": "妈妈回应瑶一瑶小肉包颜值状态",
            "url": "https://s.weibo.com/weibo?q=妈妈回应瑶一瑶小肉包颜值状态"
        },
        {
            "hot": "49万",
            "index": 10,
            "title": "刘耀文生日直播",
            "url": "https://s.weibo.com/weibo?q=刘耀文生日直播"
        },
        {
            "hot": "43万",
            "index": 11,
            "title": "广州全市五停",
            "url": "https://s.weibo.com/weibo?q=广州全市五停"
        },
        {
            "hot": "37万",
            "index": 12,
            "title": "医院通报CT报告单现不文明用语",
            "url": "https://s.weibo.com/weibo?q=医院通报CT报告单现不文明用语"
        },
        {
            "hot": "37万",
            "index": 13,
            "title": "范丞丞喝多了",
            "url": "https://s.weibo.com/weibo?q=范丞丞喝多了"
        },
        {
            "hot": "33万",
            "index": 14,
            "title": "丁泽仁国职考试通过",
            "url": "https://s.weibo.com/weibo?q=丁泽仁国职考试通过"
        },
        {
            "hot": "30万",
            "index": 15,
            "title": "繁花剧组严正声明",
            "url": "https://s.weibo.com/weibo?q=繁花剧组严正声明"
        },
        {
            "hot": "29万",
            "index": 16,
            "title": "新疆维吾尔自治区成立70周年庆祝活动",
            "url": "https://s.weibo.com/weibo?q=新疆维吾尔自治区成立70周年庆祝活动"
        },
        {
            "hot": "27万",
            "index": 17,
            "title": "28岁男子上树被自带绳子缠脖身亡",
            "url": "https://s.weibo.com/weibo?q=28岁男子上树被自带绳子缠脖身亡"
        },
        {
            "hot": "27万",
            "index": 18,
            "title": "布洛芬 能给卑职一个明示吗",
            "url": "https://s.weibo.com/weibo?q=布洛芬 能给卑职一个明示吗"
        },
        {
            "hot": "26万",
            "index": 19,
            "title": "桦加沙登陆地点确认",
            "url": "https://s.weibo.com/weibo?q=桦加沙登陆地点确认"
        },
        {
            "hot": "25万",
            "index": 20,
            "title": "性侵崔丽丽老板事发后卸任董事长",
            "url": "https://s.weibo.com/weibo?q=性侵崔丽丽老板事发后卸任董事长"
        },
        {
            "hot": "24万",
            "index": 21,
            "title": "台风前夕腾讯把企鹅拴住了",
            "url": "https://s.weibo.com/weibo?q=台风前夕腾讯把企鹅拴住了"
        },
        {
            "hot": "23万",
            "index": 22,
            "title": "深圳 胶带断货",
            "url": "https://s.weibo.com/weibo?q=深圳 胶带断货"
        },
        {
            "hot": "22万",
            "index": 23,
            "title": "月经提前vs月经推迟",
            "url": "https://s.weibo.com/weibo?q=月经提前vs月经推迟"
        },
        {
            "hot": "20万",
            "index": 24,
            "title": "赴山海是否意味着新武侠剧的没落",
            "url": "https://s.weibo.com/weibo?q=赴山海是否意味着新武侠剧的没落"
        },
        {
            "hot": "19万",
            "index": 25,
            "title": "桦加沙路径",
            "url": "https://s.weibo.com/weibo?q=桦加沙路径"
        },
        {
            "hot": "19万",
            "index": 26,
            "title": "特朗普称所有孕妇都不该用泰诺止痛",
            "url": "https://s.weibo.com/weibo?q=特朗普称所有孕妇都不该用泰诺止痛"
        },
        {
            "hot": "19万",
            "index": 27,
            "title": "等了13年的婚礼等来一句他死了",
            "url": "https://s.weibo.com/weibo?q=等了13年的婚礼等来一句他死了"
        },
        {
            "hot": "18万",
            "index": 28,
            "title": "半个娱乐圈都来长治了",
            "url": "https://s.weibo.com/weibo?q=半个娱乐圈都来长治了"
        },
        {
            "hot": "17万",
            "index": 29,
            "title": "深圳开启全市最大应急避难场所",
            "url": "https://s.weibo.com/weibo?q=深圳开启全市最大应急避难场所"
        },
        {
            "hot": "17万",
            "index": 30,
            "title": "张婧仪Burberry看秀",
            "url": "https://s.weibo.com/weibo?q=张婧仪Burberry看秀"
        },
        {
            "hot": "17万",
            "index": 31,
            "title": "闪耀暖暖屏中美人",
            "url": "https://s.weibo.com/weibo?q=闪耀暖暖屏中美人"
        },
        {
            "hot": "17万",
            "index": 32,
            "title": "大润发自营卫生巾惊现壁虎",
            "url": "https://s.weibo.com/weibo?q=大润发自营卫生巾惊现壁虎"
        },
        {
            "hot": "17万",
            "index": 33,
            "title": "冲锋衣面料终于不硬邦邦了",
            "url": "https://s.weibo.com/weibo?q=冲锋衣面料终于不硬邦邦了"
        },
        {
            "hot": "17万",
            "index": 34,
            "title": "披荆斩棘姐姐助阵路透",
            "url": "https://s.weibo.com/weibo?q=披荆斩棘姐姐助阵路透"
        },
        {
            "hot": "15万",
            "index": 35,
            "title": "还真让胡先煦追星成功了",
            "url": "https://s.weibo.com/weibo?q=还真让胡先煦追星成功了"
        },
        {
            "hot": "15万",
            "index": 36,
            "title": "吴邪私家笔记第8集30分37秒",
            "url": "https://s.weibo.com/weibo?q=吴邪私家笔记第8集30分37秒"
        },
        {
            "hot": "14万",
            "index": 37,
            "title": "遮天叶凡的反杀有多爽",
            "url": "https://s.weibo.com/weibo?q=遮天叶凡的反杀有多爽"
        },
        {
            "hot": "14万",
            "index": 38,
            "title": "风月不相关",
            "url": "https://s.weibo.com/weibo?q=风月不相关"
        },
        {
            "hot": "14万",
            "index": 39,
            "title": "李一桐被磕掉了一颗牙",
            "url": "https://s.weibo.com/weibo?q=李一桐被磕掉了一颗牙"
        },
        {
            "hot": "14万",
            "index": 40,
            "title": "瑞幸苹果拿铁文案 翻车",
            "url": "https://s.weibo.com/weibo?q=瑞幸苹果拿铁文案 翻车"
        },
        {
            "hot": "13万",
            "index": 41,
            "title": "这个造型钟楚曦来了也不行",
            "url": "https://s.weibo.com/weibo?q=这个造型钟楚曦来了也不行"
        },
        {
            "hot": "13万",
            "index": 42,
            "title": "郑希怡老得还快过台风桦加沙",
            "url": "https://s.weibo.com/weibo?q=郑希怡老得还快过台风桦加沙"
        },
        {
            "hot": "13万",
            "index": 43,
            "title": "瘦47斤发现不止身材变了",
            "url": "https://s.weibo.com/weibo?q=瘦47斤发现不止身材变了"
        },
        {
            "hot": "13万",
            "index": 44,
            "title": "梁王",
            "url": "https://s.weibo.com/weibo?q=梁王"
        },
        {
            "hot": "13万",
            "index": 45,
            "title": "华为发布会",
            "url": "https://s.weibo.com/weibo?q=华为发布会"
        },
        {
            "hot": "12万",
            "index": 46,
            "title": "桦加沙强度",
            "url": "https://s.weibo.com/weibo?q=桦加沙强度"
        },
        {
            "hot": "12万",
            "index": 47,
            "title": "宋轶怎么美成这样了",
            "url": "https://s.weibo.com/weibo?q=宋轶怎么美成这样了"
        },
        {
            "hot": "12万",
            "index": 48,
            "title": "飞机两次进入桦加沙中心区域",
            "url": "https://s.weibo.com/weibo?q=飞机两次进入桦加沙中心区域"
        },
        {
            "hot": "12万",
            "index": 49,
            "title": "韦雪回应9亿分手费",
            "url": "https://s.weibo.com/weibo?q=韦雪回应9亿分手费"
        },
        {
            "hot": "11万",
            "index": 50,
            "title": "敖瑞鹏晒朝雪录庆功宴合照",
            "url": "https://s.weibo.com/weibo?q=敖瑞鹏晒朝雪录庆功宴合照"
        },
        {
            "hot": "11万",
            "index": 51,
            "title": "T1队服价格",
            "url": "https://s.weibo.com/weibo?q=T1队服价格"
        },
        {
            "hot": "11万",
            "index": 52,
            "title": "乔欣变美了",
            "url": "https://s.weibo.com/weibo?q=乔欣变美了"
        }
    ],
    "request_id": "4aeec9a651f8af1ac9c8881b"
}